{
  "package": {
    "name": "Aspire.Azure.Security.KeyVault",
    "version": "13.2.0",
    "targetFramework": "net10.0",
    "sourceRepository": "https://github.com/dotnet/aspire",
    "sourceCommit": "aad16017893bd769e0634c47fb007f1454735f11"
  },
  "types": [
    {
      "name": "AzureSecurityKeyVaultSettings",
      "fullName": "Aspire.Azure.Security.KeyVault.AzureSecurityKeyVaultSettings",
      "namespace": "Aspire.Azure.Security.KeyVault",
      "kind": "class",
      "accessibility": "public",
      "isSealed": true,
      "interfaces": [
        "Aspire.Azure.Common.IConnectionStringSettings"
      ],
      "docs": {
        "summary": [
          {
            "kind": "text",
            "text": " Provides the client configuration settings for connecting to Azure Key Vault. "
          }
        ]
      },
      "sourceFile": "src/Components/Aspire.Azure.Security.KeyVault/AzureSecurityKeyVaultSettings.cs",
      "sourceLines": "13-13",
      "members": [
        {
          "name": ".ctor",
          "kind": "constructor",
          "accessibility": "public",
          "signature": "public AzureSecurityKeyVaultSettings.AzureSecurityKeyVaultSettings()",
          "returnType": "void"
        },
        {
          "name": "Credential",
          "kind": "property",
          "accessibility": "public",
          "signature": "public TokenCredential? AzureSecurityKeyVaultSettings.Credential",
          "returnType": "Azure.Core.TokenCredential?",
          "isReturnNullable": true,
          "hasGet": true,
          "hasSet": true,
          "docs": {
            "summary": [
              {
                "kind": "text",
                "text": " Gets or sets the credential used to authenticate to the Azure Key Vault. "
              }
            ]
          },
          "sourceFile": "src/Components/Aspire.Azure.Security.KeyVault/AzureSecurityKeyVaultSettings.cs"
        },
        {
          "name": "DisableHealthChecks",
          "kind": "property",
          "accessibility": "public",
          "signature": "public bool AzureSecurityKeyVaultSettings.DisableHealthChecks",
          "returnType": "bool",
          "hasGet": true,
          "hasSet": true,
          "docs": {
            "summary": [
              {
                "kind": "text",
                "text": " Gets or sets a boolean value that indicates whether the Key Vault health check is disabled or not. "
              }
            ],
            "value": [
              {
                "kind": "text",
                "text": " The default value is "
              },
              {
                "kind": "langword",
                "value": "false"
              },
              {
                "kind": "text",
                "text": ". "
              }
            ]
          },
          "sourceFile": "src/Components/Aspire.Azure.Security.KeyVault/AzureSecurityKeyVaultSettings.cs"
        },
        {
          "name": "DisableTracing",
          "kind": "property",
          "accessibility": "public",
          "signature": "public bool AzureSecurityKeyVaultSettings.DisableTracing",
          "returnType": "bool",
          "hasGet": true,
          "hasSet": true,
          "docs": {
            "summary": [
              {
                "kind": "text",
                "text": " Gets or sets a boolean value that indicates whether the OpenTelemetry tracing is disabled or not. "
              }
            ],
            "value": [
              {
                "kind": "text",
                "text": " The default value is "
              },
              {
                "kind": "langword",
                "value": "false"
              },
              {
                "kind": "text",
                "text": ". "
              }
            ]
          },
          "sourceFile": "src/Components/Aspire.Azure.Security.KeyVault/AzureSecurityKeyVaultSettings.cs"
        },
        {
          "name": "VaultUri",
          "kind": "property",
          "accessibility": "public",
          "signature": "public Uri? AzureSecurityKeyVaultSettings.VaultUri",
          "returnType": "System.Uri?",
          "isReturnNullable": true,
          "hasGet": true,
          "hasSet": true,
          "docs": {
            "summary": [
              {
                "kind": "text",
                "text": " A "
              },
              {
                "kind": "cref",
                "value": "T:System.Uri"
              },
              {
                "kind": "text",
                "text": " to the vault on which the client operates. Appears as \"DNS Name\" in the Azure portal. If you have a secret "
              },
              {
                "kind": "cref",
                "value": "T:System.Uri"
              },
              {
                "kind": "text",
                "text": ", use "
              },
              {
                "kind": "cref",
                "value": "T:Azure.Security.KeyVault.Secrets.KeyVaultSecretIdentifier"
              },
              {
                "kind": "text",
                "text": " to parse the "
              },
              {
                "kind": "cref",
                "value": "P:Azure.Security.KeyVault.Secrets.KeyVaultSecretIdentifier.VaultUri"
              },
              {
                "kind": "text",
                "text": " and other information. You should validate that this URI references a valid Key Vault resource. See "
              },
              {
                "kind": "href",
                "value": "https://aka.ms/azsdk/blog/vault-uri"
              },
              {
                "kind": "text",
                "text": " for details. "
              }
            ]
          },
          "sourceFile": "src/Components/Aspire.Azure.Security.KeyVault/AzureSecurityKeyVaultSettings.cs"
        }
      ]
    },
    {
      "name": "AspireKeyVaultExtensions",
      "fullName": "Microsoft.Extensions.Hosting.AspireKeyVaultExtensions",
      "namespace": "Microsoft.Extensions.Hosting",
      "kind": "class",
      "accessibility": "public",
      "isStatic": true,
      "docs": {
        "summary": [
          {
            "kind": "text",
            "text": " Provides extension methods for registering and configuring Azure Key Vault secrets in an Aspire application. "
          }
        ]
      },
      "sourceFile": "src/Components/Aspire.Azure.Security.KeyVault/AspireKeyVaultExtensions.cs",
      "sourceLines": "20-20",
      "members": [
        {
          "name": "AddAzureKeyVaultCertificateClient",
          "kind": "method",
          "accessibility": "public",
          "signature": "public static void AspireKeyVaultExtensions.AddAzureKeyVaultCertificateClient(this IHostApplicationBuilder builder, string connectionName, Action<AzureSecurityKeyVaultSettings>? configureSettings = null, Action<IAzureClientBuilder<CertificateClient, CertificateClientOptions>>? configureClientBuilder = null)",
          "returnType": "void",
          "isStatic": true,
          "isExtension": true,
          "parameters": [
            {
              "name": "builder",
              "type": "Microsoft.Extensions.Hosting.IHostApplicationBuilder",
              "modifier": "this"
            },
            {
              "name": "connectionName",
              "type": "string"
            },
            {
              "name": "configureSettings",
              "type": "System.Action<Aspire.Azure.Security.KeyVault.AzureSecurityKeyVaultSettings>?",
              "isNullable": true,
              "isOptional": true
            },
            {
              "name": "configureClientBuilder",
              "type": "System.Action<Azure.Core.Extensions.IAzureClientBuilder<Azure.Security.KeyVault.Certificates.CertificateClient, Azure.Security.KeyVault.Certificates.CertificateClientOptions>>?",
              "isNullable": true,
              "isOptional": true
            }
          ],
          "docs": {
            "summary": [
              {
                "kind": "text",
                "text": " Registers "
              },
              {
                "kind": "cref",
                "value": "T:Azure.Security.KeyVault.Certificates.CertificateClient"
              },
              {
                "kind": "text",
                "text": " as a singleton in the services provided by the "
              },
              {
                "kind": "paramref",
                "value": "builder"
              },
              {
                "kind": "text",
                "text": ". "
              }
            ],
            "remarks": [
              {
                "kind": "text",
                "text": "Reads the configuration from \"Aspire:Azure:Security:KeyVault:{name}\" section."
              }
            ],
            "parameters": {
              "builder": [
                {
                  "kind": "text",
                  "text": "The "
                },
                {
                  "kind": "cref",
                  "value": "T:Microsoft.Extensions.Hosting.IHostApplicationBuilder"
                },
                {
                  "kind": "text",
                  "text": " to read config from and add services to."
                }
              ],
              "configureClientBuilder": [
                {
                  "kind": "text",
                  "text": "An optional method that can be used for customizing the "
                },
                {
                  "kind": "cref",
                  "value": "T:Azure.Core.Extensions.IAzureClientBuilder`2"
                },
                {
                  "kind": "text",
                  "text": "."
                }
              ],
              "configureSettings": [
                {
                  "kind": "text",
                  "text": "An optional method that can be used for customizing the "
                },
                {
                  "kind": "cref",
                  "value": "T:Aspire.Azure.Security.KeyVault.AzureSecurityKeyVaultSettings"
                },
                {
                  "kind": "text",
                  "text": ". It's invoked after the settings are read from the configuration."
                }
              ],
              "connectionName": [
                {
                  "kind": "text",
                  "text": "A name used to retrieve the connection string from the ConnectionStrings configuration section."
                }
              ]
            },
            "exceptions": [
              {
                "type": "T:System.InvalidOperationException",
                "description": [
                  {
                    "kind": "text",
                    "text": "Thrown when mandatory "
                  },
                  {
                    "kind": "cref",
                    "value": "P:Aspire.Azure.Security.KeyVault.AzureSecurityKeyVaultSettings.VaultUri"
                  },
                  {
                    "kind": "text",
                    "text": " is not provided."
                  }
                ]
              }
            ]
          },
          "sourceFile": "src/Components/Aspire.Azure.Security.KeyVault/AspireKeyVaultExtensions.cs",
          "sourceLines": "85-90"
        },
        {
          "name": "AddAzureKeyVaultClient",
          "kind": "method",
          "accessibility": "public",
          "signature": "public static void AspireKeyVaultExtensions.AddAzureKeyVaultClient(this IHostApplicationBuilder builder, string connectionName, Action<AzureSecurityKeyVaultSettings>? configureSettings = null, Action<IAzureClientBuilder<SecretClient, SecretClientOptions>>? configureClientBuilder = null)",
          "returnType": "void",
          "isStatic": true,
          "isExtension": true,
          "parameters": [
            {
              "name": "builder",
              "type": "Microsoft.Extensions.Hosting.IHostApplicationBuilder",
              "modifier": "this"
            },
            {
              "name": "connectionName",
              "type": "string"
            },
            {
              "name": "configureSettings",
              "type": "System.Action<Aspire.Azure.Security.KeyVault.AzureSecurityKeyVaultSettings>?",
              "isNullable": true,
              "isOptional": true
            },
            {
              "name": "configureClientBuilder",
              "type": "System.Action<Azure.Core.Extensions.IAzureClientBuilder<Azure.Security.KeyVault.Secrets.SecretClient, Azure.Security.KeyVault.Secrets.SecretClientOptions>>?",
              "isNullable": true,
              "isOptional": true
            }
          ],
          "docs": {
            "summary": [
              {
                "kind": "text",
                "text": " Registers "
              },
              {
                "kind": "cref",
                "value": "T:Azure.Security.KeyVault.Secrets.SecretClient"
              },
              {
                "kind": "text",
                "text": " as a singleton in the services provided by the "
              },
              {
                "kind": "paramref",
                "value": "builder"
              },
              {
                "kind": "text",
                "text": ". Enables retries, corresponding health check, logging and telemetry. "
              }
            ],
            "remarks": [
              {
                "kind": "text",
                "text": "Reads the configuration from \"Aspire:Azure:Security:KeyVault\" section."
              }
            ],
            "parameters": {
              "builder": [
                {
                  "kind": "text",
                  "text": "The "
                },
                {
                  "kind": "cref",
                  "value": "T:Microsoft.Extensions.Hosting.IHostApplicationBuilder"
                },
                {
                  "kind": "text",
                  "text": " to read config from and add services to."
                }
              ],
              "configureClientBuilder": [
                {
                  "kind": "text",
                  "text": "An optional method that can be used for customizing the "
                },
                {
                  "kind": "cref",
                  "value": "T:Azure.Core.Extensions.IAzureClientBuilder`2"
                },
                {
                  "kind": "text",
                  "text": "."
                }
              ],
              "configureSettings": [
                {
                  "kind": "text",
                  "text": "An optional method that can be used for customizing the "
                },
                {
                  "kind": "cref",
                  "value": "T:Aspire.Azure.Security.KeyVault.AzureSecurityKeyVaultSettings"
                },
                {
                  "kind": "text",
                  "text": ". It's invoked after the settings are read from the configuration."
                }
              ],
              "connectionName": [
                {
                  "kind": "text",
                  "text": "A name used to retrieve the connection string from the ConnectionStrings configuration section."
                }
              ]
            },
            "exceptions": [
              {
                "type": "T:System.InvalidOperationException",
                "description": [
                  {
                    "kind": "text",
                    "text": "Thrown when mandatory "
                  },
                  {
                    "kind": "cref",
                    "value": "P:Aspire.Azure.Security.KeyVault.AzureSecurityKeyVaultSettings.VaultUri"
                  },
                  {
                    "kind": "text",
                    "text": " is not provided."
                  }
                ]
              }
            ]
          },
          "sourceFile": "src/Components/Aspire.Azure.Security.KeyVault/AspireKeyVaultExtensions.cs",
          "sourceLines": "40-45"
        },
        {
          "name": "AddAzureKeyVaultKeyClient",
          "kind": "method",
          "accessibility": "public",
          "signature": "public static void AspireKeyVaultExtensions.AddAzureKeyVaultKeyClient(this IHostApplicationBuilder builder, string connectionName, Action<AzureSecurityKeyVaultSettings>? configureSettings = null, Action<IAzureClientBuilder<KeyClient, KeyClientOptions>>? configureClientBuilder = null)",
          "returnType": "void",
          "isStatic": true,
          "isExtension": true,
          "parameters": [
            {
              "name": "builder",
              "type": "Microsoft.Extensions.Hosting.IHostApplicationBuilder",
              "modifier": "this"
            },
            {
              "name": "connectionName",
              "type": "string"
            },
            {
              "name": "configureSettings",
              "type": "System.Action<Aspire.Azure.Security.KeyVault.AzureSecurityKeyVaultSettings>?",
              "isNullable": true,
              "isOptional": true
            },
            {
              "name": "configureClientBuilder",
              "type": "System.Action<Azure.Core.Extensions.IAzureClientBuilder<Azure.Security.KeyVault.Keys.KeyClient, Azure.Security.KeyVault.Keys.KeyClientOptions>>?",
              "isNullable": true,
              "isOptional": true
            }
          ],
          "docs": {
            "summary": [
              {
                "kind": "text",
                "text": " Registers "
              },
              {
                "kind": "cref",
                "value": "T:Azure.Security.KeyVault.Keys.KeyClient"
              },
              {
                "kind": "text",
                "text": " as a singleton in the services provided by the "
              },
              {
                "kind": "paramref",
                "value": "builder"
              },
              {
                "kind": "text",
                "text": ". "
              }
            ],
            "remarks": [
              {
                "kind": "text",
                "text": "Reads the configuration from \"Aspire:Azure:Security:KeyVault:{name}\" section."
              }
            ],
            "parameters": {
              "builder": [
                {
                  "kind": "text",
                  "text": "The "
                },
                {
                  "kind": "cref",
                  "value": "T:Microsoft.Extensions.Hosting.IHostApplicationBuilder"
                },
                {
                  "kind": "text",
                  "text": " to read config from and add services to."
                }
              ],
              "configureClientBuilder": [
                {
                  "kind": "text",
                  "text": "An optional method that can be used for customizing the "
                },
                {
                  "kind": "cref",
                  "value": "T:Azure.Core.Extensions.IAzureClientBuilder`2"
                },
                {
                  "kind": "text",
                  "text": "."
                }
              ],
              "configureSettings": [
                {
                  "kind": "text",
                  "text": "An optional method that can be used for customizing the "
                },
                {
                  "kind": "cref",
                  "value": "T:Aspire.Azure.Security.KeyVault.AzureSecurityKeyVaultSettings"
                },
                {
                  "kind": "text",
                  "text": ". It's invoked after the settings are read from the configuration."
                }
              ],
              "connectionName": [
                {
                  "kind": "text",
                  "text": "A name used to retrieve the connection string from the ConnectionStrings configuration section."
                }
              ]
            },
            "exceptions": [
              {
                "type": "T:System.InvalidOperationException",
                "description": [
                  {
                    "kind": "text",
                    "text": "Thrown when mandatory "
                  },
                  {
                    "kind": "cref",
                    "value": "P:Aspire.Azure.Security.KeyVault.AzureSecurityKeyVaultSettings.VaultUri"
                  },
                  {
                    "kind": "text",
                    "text": " is not provided."
                  }
                ]
              }
            ]
          },
          "sourceFile": "src/Components/Aspire.Azure.Security.KeyVault/AspireKeyVaultExtensions.cs",
          "sourceLines": "129-134"
        },
        {
          "name": "AddAzureKeyVaultSecrets",
          "kind": "method",
          "accessibility": "public",
          "signature": "public static void AspireKeyVaultExtensions.AddAzureKeyVaultSecrets(this IConfigurationManager configurationManager, string connectionName, Action<AzureSecurityKeyVaultSettings>? configureSettings = null, Action<SecretClientOptions>? configureClientOptions = null, AzureKeyVaultConfigurationOptions? options = null)",
          "returnType": "void",
          "isStatic": true,
          "isExtension": true,
          "parameters": [
            {
              "name": "configurationManager",
              "type": "Microsoft.Extensions.Configuration.IConfigurationManager",
              "modifier": "this"
            },
            {
              "name": "connectionName",
              "type": "string"
            },
            {
              "name": "configureSettings",
              "type": "System.Action<Aspire.Azure.Security.KeyVault.AzureSecurityKeyVaultSettings>?",
              "isNullable": true,
              "isOptional": true
            },
            {
              "name": "configureClientOptions",
              "type": "System.Action<Azure.Security.KeyVault.Secrets.SecretClientOptions>?",
              "isNullable": true,
              "isOptional": true
            },
            {
              "name": "options",
              "type": "Azure.Extensions.AspNetCore.Configuration.Secrets.AzureKeyVaultConfigurationOptions?",
              "isNullable": true,
              "isOptional": true
            }
          ],
          "docs": {
            "summary": [
              {
                "kind": "text",
                "text": " Adds the Azure KeyVault secrets to be configuration values in the "
              },
              {
                "kind": "paramref",
                "value": "configurationManager"
              },
              {
                "kind": "text",
                "text": ". "
              }
            ],
            "parameters": {
              "configurationManager": [
                {
                  "kind": "text",
                  "text": "The "
                },
                {
                  "kind": "cref",
                  "value": "T:Microsoft.Extensions.Configuration.IConfigurationManager"
                },
                {
                  "kind": "text",
                  "text": " to add the secrets to."
                }
              ],
              "configureClientOptions": [
                {
                  "kind": "text",
                  "text": "An optional method that can be used for customizing the "
                },
                {
                  "kind": "cref",
                  "value": "T:Azure.Security.KeyVault.Secrets.SecretClientOptions"
                },
                {
                  "kind": "text",
                  "text": "."
                }
              ],
              "configureSettings": [
                {
                  "kind": "text",
                  "text": "An optional method that can be used for customizing the "
                },
                {
                  "kind": "cref",
                  "value": "T:Aspire.Azure.Security.KeyVault.AzureSecurityKeyVaultSettings"
                },
                {
                  "kind": "text",
                  "text": ". It's invoked after the settings are read from the configuration."
                }
              ],
              "connectionName": [
                {
                  "kind": "text",
                  "text": "A name used to retrieve the connection string from the ConnectionStrings configuration section."
                }
              ],
              "options": [
                {
                  "kind": "text",
                  "text": "An optional "
                },
                {
                  "kind": "cref",
                  "value": "T:Azure.Extensions.AspNetCore.Configuration.Secrets.AzureKeyVaultConfigurationOptions"
                },
                {
                  "kind": "text",
                  "text": " instance to configure the behavior of the configuration provider."
                }
              ]
            }
          },
          "sourceFile": "src/Components/Aspire.Azure.Security.KeyVault/AspireKeyVaultExtensions.cs",
          "sourceLines": "173-178"
        },
        {
          "name": "AddKeyedAzureKeyVaultCertificateClient",
          "kind": "method",
          "accessibility": "public",
          "signature": "public static void AspireKeyVaultExtensions.AddKeyedAzureKeyVaultCertificateClient(this IHostApplicationBuilder builder, string name, Action<AzureSecurityKeyVaultSettings>? configureSettings = null, Action<IAzureClientBuilder<CertificateClient, CertificateClientOptions>>? configureClientBuilder = null)",
          "returnType": "void",
          "isStatic": true,
          "isExtension": true,
          "parameters": [
            {
              "name": "builder",
              "type": "Microsoft.Extensions.Hosting.IHostApplicationBuilder",
              "modifier": "this"
            },
            {
              "name": "name",
              "type": "string"
            },
            {
              "name": "configureSettings",
              "type": "System.Action<Aspire.Azure.Security.KeyVault.AzureSecurityKeyVaultSettings>?",
              "isNullable": true,
              "isOptional": true
            },
            {
              "name": "configureClientBuilder",
              "type": "System.Action<Azure.Core.Extensions.IAzureClientBuilder<Azure.Security.KeyVault.Certificates.CertificateClient, Azure.Security.KeyVault.Certificates.CertificateClientOptions>>?",
              "isNullable": true,
              "isOptional": true
            }
          ],
          "docs": {
            "summary": [
              {
                "kind": "text",
                "text": " Registers "
              },
              {
                "kind": "cref",
                "value": "T:Azure.Security.KeyVault.Certificates.CertificateClient"
              },
              {
                "kind": "text",
                "text": " as a singleton for given "
              },
              {
                "kind": "paramref",
                "value": "name"
              },
              {
                "kind": "text",
                "text": " in the services provided by the "
              },
              {
                "kind": "paramref",
                "value": "builder"
              },
              {
                "kind": "text",
                "text": ". "
              }
            ],
            "remarks": [
              {
                "kind": "text",
                "text": "Reads the configuration from \"Aspire:Azure:Security:KeyVault:{name}\" section."
              }
            ],
            "parameters": {
              "builder": [
                {
                  "kind": "text",
                  "text": "The "
                },
                {
                  "kind": "cref",
                  "value": "T:Microsoft.Extensions.Hosting.IHostApplicationBuilder"
                },
                {
                  "kind": "text",
                  "text": " to read config from and add services to."
                }
              ],
              "configureClientBuilder": [
                {
                  "kind": "text",
                  "text": "An optional method that can be used for customizing the "
                },
                {
                  "kind": "cref",
                  "value": "T:Azure.Core.Extensions.IAzureClientBuilder`2"
                },
                {
                  "kind": "text",
                  "text": "."
                }
              ],
              "configureSettings": [
                {
                  "kind": "text",
                  "text": "An optional method that can be used for customizing the "
                },
                {
                  "kind": "cref",
                  "value": "T:Aspire.Azure.Security.KeyVault.AzureSecurityKeyVaultSettings"
                },
                {
                  "kind": "text",
                  "text": ". It's invoked after the settings are read from the configuration."
                }
              ],
              "name": [
                {
                  "kind": "text",
                  "text": "The name of the component, which is used as the "
                },
                {
                  "kind": "cref",
                  "value": "P:Microsoft.Extensions.DependencyInjection.ServiceDescriptor.ServiceKey"
                },
                {
                  "kind": "text",
                  "text": " of the service and also to retrieve the connection information from the ConnectionStrings configuration section."
                }
              ]
            },
            "exceptions": [
              {
                "type": "T:System.InvalidOperationException",
                "description": [
                  {
                    "kind": "text",
                    "text": "Thrown when mandatory "
                  },
                  {
                    "kind": "cref",
                    "value": "P:Aspire.Azure.Security.KeyVault.AzureSecurityKeyVaultSettings.VaultUri"
                  },
                  {
                    "kind": "text",
                    "text": " is not provided."
                  }
                ]
              }
            ]
          },
          "sourceFile": "src/Components/Aspire.Azure.Security.KeyVault/AspireKeyVaultExtensions.cs",
          "sourceLines": "107-112"
        },
        {
          "name": "AddKeyedAzureKeyVaultClient",
          "kind": "method",
          "accessibility": "public",
          "signature": "public static void AspireKeyVaultExtensions.AddKeyedAzureKeyVaultClient(this IHostApplicationBuilder builder, string name, Action<AzureSecurityKeyVaultSettings>? configureSettings = null, Action<IAzureClientBuilder<SecretClient, SecretClientOptions>>? configureClientBuilder = null)",
          "returnType": "void",
          "isStatic": true,
          "isExtension": true,
          "parameters": [
            {
              "name": "builder",
              "type": "Microsoft.Extensions.Hosting.IHostApplicationBuilder",
              "modifier": "this"
            },
            {
              "name": "name",
              "type": "string"
            },
            {
              "name": "configureSettings",
              "type": "System.Action<Aspire.Azure.Security.KeyVault.AzureSecurityKeyVaultSettings>?",
              "isNullable": true,
              "isOptional": true
            },
            {
              "name": "configureClientBuilder",
              "type": "System.Action<Azure.Core.Extensions.IAzureClientBuilder<Azure.Security.KeyVault.Secrets.SecretClient, Azure.Security.KeyVault.Secrets.SecretClientOptions>>?",
              "isNullable": true,
              "isOptional": true
            }
          ],
          "docs": {
            "summary": [
              {
                "kind": "text",
                "text": " Registers "
              },
              {
                "kind": "cref",
                "value": "T:Azure.Security.KeyVault.Secrets.SecretClient"
              },
              {
                "kind": "text",
                "text": " as a singleton for given "
              },
              {
                "kind": "paramref",
                "value": "name"
              },
              {
                "kind": "text",
                "text": " in the services provided by the "
              },
              {
                "kind": "paramref",
                "value": "builder"
              },
              {
                "kind": "text",
                "text": ". Enables retries, corresponding health check, logging and telemetry. "
              }
            ],
            "remarks": [
              {
                "kind": "text",
                "text": "Reads the configuration from \"Aspire:Azure:Security:KeyVault:{name}\" section."
              }
            ],
            "parameters": {
              "builder": [
                {
                  "kind": "text",
                  "text": "The "
                },
                {
                  "kind": "cref",
                  "value": "T:Microsoft.Extensions.Hosting.IHostApplicationBuilder"
                },
                {
                  "kind": "text",
                  "text": " to read config from and add services to."
                }
              ],
              "configureClientBuilder": [
                {
                  "kind": "text",
                  "text": "An optional method that can be used for customizing the "
                },
                {
                  "kind": "cref",
                  "value": "T:Azure.Core.Extensions.IAzureClientBuilder`2"
                },
                {
                  "kind": "text",
                  "text": "."
                }
              ],
              "configureSettings": [
                {
                  "kind": "text",
                  "text": "An optional method that can be used for customizing the "
                },
                {
                  "kind": "cref",
                  "value": "T:Aspire.Azure.Security.KeyVault.AzureSecurityKeyVaultSettings"
                },
                {
                  "kind": "text",
                  "text": ". It's invoked after the settings are read from the configuration."
                }
              ],
              "name": [
                {
                  "kind": "text",
                  "text": "The name of the component, which is used as the "
                },
                {
                  "kind": "cref",
                  "value": "P:Microsoft.Extensions.DependencyInjection.ServiceDescriptor.ServiceKey"
                },
                {
                  "kind": "text",
                  "text": " of the service and also to retrieve the connection information from the ConnectionStrings configuration section."
                }
              ]
            },
            "exceptions": [
              {
                "type": "T:System.InvalidOperationException",
                "description": [
                  {
                    "kind": "text",
                    "text": "Thrown when mandatory "
                  },
                  {
                    "kind": "cref",
                    "value": "P:Aspire.Azure.Security.KeyVault.AzureSecurityKeyVaultSettings.VaultUri"
                  },
                  {
                    "kind": "text",
                    "text": " is not provided."
                  }
                ]
              }
            ]
          },
          "sourceFile": "src/Components/Aspire.Azure.Security.KeyVault/AspireKeyVaultExtensions.cs",
          "sourceLines": "63-68"
        },
        {
          "name": "AddKeyedAzureKeyVaultKeyClient",
          "kind": "method",
          "accessibility": "public",
          "signature": "public static void AspireKeyVaultExtensions.AddKeyedAzureKeyVaultKeyClient(this IHostApplicationBuilder builder, string name, Action<AzureSecurityKeyVaultSettings>? configureSettings = null, Action<IAzureClientBuilder<KeyClient, KeyClientOptions>>? configureClientBuilder = null)",
          "returnType": "void",
          "isStatic": true,
          "isExtension": true,
          "parameters": [
            {
              "name": "builder",
              "type": "Microsoft.Extensions.Hosting.IHostApplicationBuilder",
              "modifier": "this"
            },
            {
              "name": "name",
              "type": "string"
            },
            {
              "name": "configureSettings",
              "type": "System.Action<Aspire.Azure.Security.KeyVault.AzureSecurityKeyVaultSettings>?",
              "isNullable": true,
              "isOptional": true
            },
            {
              "name": "configureClientBuilder",
              "type": "System.Action<Azure.Core.Extensions.IAzureClientBuilder<Azure.Security.KeyVault.Keys.KeyClient, Azure.Security.KeyVault.Keys.KeyClientOptions>>?",
              "isNullable": true,
              "isOptional": true
            }
          ],
          "docs": {
            "summary": [
              {
                "kind": "text",
                "text": " Registers "
              },
              {
                "kind": "cref",
                "value": "T:Azure.Security.KeyVault.Keys.KeyClient"
              },
              {
                "kind": "text",
                "text": " as a singleton for given "
              },
              {
                "kind": "paramref",
                "value": "name"
              },
              {
                "kind": "text",
                "text": " in the services provided by the "
              },
              {
                "kind": "paramref",
                "value": "builder"
              },
              {
                "kind": "text",
                "text": ". "
              }
            ],
            "remarks": [
              {
                "kind": "text",
                "text": "Reads the configuration from \"Aspire:Azure:Security:KeyVault:{name}\" section."
              }
            ],
            "parameters": {
              "builder": [
                {
                  "kind": "text",
                  "text": "The "
                },
                {
                  "kind": "cref",
                  "value": "T:Microsoft.Extensions.Hosting.IHostApplicationBuilder"
                },
                {
                  "kind": "text",
                  "text": " to read config from and add services to."
                }
              ],
              "configureClientBuilder": [
                {
                  "kind": "text",
                  "text": "An optional method that can be used for customizing the "
                },
                {
                  "kind": "cref",
                  "value": "T:Azure.Core.Extensions.IAzureClientBuilder`2"
                },
                {
                  "kind": "text",
                  "text": "."
                }
              ],
              "configureSettings": [
                {
                  "kind": "text",
                  "text": "An optional method that can be used for customizing the "
                },
                {
                  "kind": "cref",
                  "value": "T:Aspire.Azure.Security.KeyVault.AzureSecurityKeyVaultSettings"
                },
                {
                  "kind": "text",
                  "text": ". It's invoked after the settings are read from the configuration."
                }
              ],
              "name": [
                {
                  "kind": "text",
                  "text": "The name of the component, which is used as the "
                },
                {
                  "kind": "cref",
                  "value": "P:Microsoft.Extensions.DependencyInjection.ServiceDescriptor.ServiceKey"
                },
                {
                  "kind": "text",
                  "text": " of the service and also to retrieve the connection information from the ConnectionStrings configuration section."
                }
              ]
            },
            "exceptions": [
              {
                "type": "T:System.InvalidOperationException",
                "description": [
                  {
                    "kind": "text",
                    "text": "Thrown when mandatory "
                  },
                  {
                    "kind": "cref",
                    "value": "P:Aspire.Azure.Security.KeyVault.AzureSecurityKeyVaultSettings.VaultUri"
                  },
                  {
                    "kind": "text",
                    "text": " is not provided."
                  }
                ]
              }
            ]
          },
          "sourceFile": "src/Components/Aspire.Azure.Security.KeyVault/AspireKeyVaultExtensions.cs",
          "sourceLines": "151-156"
        }
      ]
    }
  ]
}