{
  "package": {
    "name": "CommunityToolkit.Aspire.Hosting.Azure.DataApiBuilder",
    "version": "13.1.1",
    "targetFramework": "net10.0",
    "sourceRepository": "https://github.com/CommunityToolkit/Aspire",
    "sourceCommit": "67afcca30f02c18687f9c5219313710af9706630"
  },
  "types": [
    {
      "name": "DataApiBuilderHostingExtension",
      "fullName": "Aspire.Hosting.DataApiBuilderHostingExtension",
      "namespace": "Aspire.Hosting",
      "kind": "class",
      "accessibility": "public",
      "isStatic": true,
      "docs": {
        "summary": [
          {
            "kind": "text",
            "text": " Provides extension methods for adding DataApiBuilder api to an "
          },
          {
            "kind": "cref",
            "value": "T:Aspire.Hosting.IDistributedApplicationBuilder"
          },
          {
            "kind": "text",
            "text": ". "
          }
        ]
      },
      "sourceFile": "src/CommunityToolkit.Aspire.Hosting.Azure.DataApiBuilder/DataApiBuilderHostingExtension.cs",
      "sourceLines": "28-28",
      "members": [
        {
          "name": "AddDataAPIBuilder",
          "kind": "method",
          "accessibility": "public",
          "signature": "public static IResourceBuilder<DataApiBuilderContainerResource> DataApiBuilderHostingExtension.AddDataAPIBuilder(this IDistributedApplicationBuilder builder, string name, params string[] configFilePaths)",
          "returnType": "Aspire.Hosting.ApplicationModel.IResourceBuilder<Aspire.Hosting.ApplicationModel.DataApiBuilderContainerResource>",
          "isStatic": true,
          "isExtension": true,
          "parameters": [
            {
              "name": "builder",
              "type": "Aspire.Hosting.IDistributedApplicationBuilder",
              "modifier": "this"
            },
            {
              "name": "name",
              "type": "string"
            },
            {
              "name": "configFilePaths",
              "type": "string[]",
              "modifier": "params"
            }
          ],
          "docs": {
            "summary": [
              {
                "kind": "text",
                "text": " Adds a DataAPIBuilder application to the application model. Executes the pre-built containerized DataAPIBuilder engine. "
              }
            ],
            "remarks": [
              {
                "kind": "text",
                "text": " At this time, this .NET Aspire DAB integration only supports HTTPS ports. You can "
              },
              {
                "kind": "href",
                "text": "deploy DAB with HTTPS and custom certs",
                "value": "https://learn.microsoft.com/en-us/aspnet/core/security/docker-https?view=aspnetcore-8.0#running-pre-built-container-images-with-https"
              },
              {
                "kind": "text",
                "text": " in production. "
              }
            ],
            "returns": [
              {
                "kind": "text",
                "text": "A reference to the "
              },
              {
                "kind": "cref",
                "value": "T:Aspire.Hosting.ApplicationModel.IResourceBuilder`1"
              },
              {
                "kind": "text",
                "text": "."
              }
            ],
            "parameters": {
              "builder": [
                {
                  "kind": "text",
                  "text": "The "
                },
                {
                  "kind": "cref",
                  "value": "T:Aspire.Hosting.IDistributedApplicationBuilder"
                },
                {
                  "kind": "text",
                  "text": " to add the resource to."
                }
              ],
              "configFilePaths": [
                {
                  "kind": "text",
                  "text": "The path to the config or schema file(s) for Data API Builder."
                }
              ],
              "name": [
                {
                  "kind": "text",
                  "text": "The name of the resource."
                }
              ]
            }
          },
          "sourceFile": "src/CommunityToolkit.Aspire.Hosting.Azure.DataApiBuilder/DataApiBuilderHostingExtension.cs",
          "sourceLines": "28-28"
        },
        {
          "name": "AddDataAPIBuilder",
          "kind": "method",
          "accessibility": "public",
          "signature": "public static IResourceBuilder<DataApiBuilderContainerResource> DataApiBuilderHostingExtension.AddDataAPIBuilder(this IDistributedApplicationBuilder builder, string name, int? httpPort = null, params string[] configFilePaths)",
          "returnType": "Aspire.Hosting.ApplicationModel.IResourceBuilder<Aspire.Hosting.ApplicationModel.DataApiBuilderContainerResource>",
          "isStatic": true,
          "isExtension": true,
          "parameters": [
            {
              "name": "builder",
              "type": "Aspire.Hosting.IDistributedApplicationBuilder",
              "modifier": "this"
            },
            {
              "name": "name",
              "type": "string"
            },
            {
              "name": "httpPort",
              "type": "int?",
              "isNullable": true,
              "isOptional": true
            },
            {
              "name": "configFilePaths",
              "type": "string[]",
              "modifier": "params"
            }
          ],
          "docs": {
            "summary": [
              {
                "kind": "text",
                "text": " Adds a DataAPIBuilder application to the application model. Executes the pre-built containerized DataAPIBuilder engine. "
              }
            ],
            "remarks": [
              {
                "kind": "text",
                "text": " At this time, this .NET Aspire DAB integration only supports HTTPS ports. You can "
              },
              {
                "kind": "href",
                "text": "deploy DAB with HTTPS and custom certs",
                "value": "https://learn.microsoft.com/en-us/aspnet/core/security/docker-https?view=aspnetcore-8.0#running-pre-built-container-images-with-https"
              },
              {
                "kind": "text",
                "text": " in production. "
              }
            ],
            "returns": [
              {
                "kind": "text",
                "text": "A reference to the "
              },
              {
                "kind": "cref",
                "value": "T:Aspire.Hosting.ApplicationModel.IResourceBuilder`1"
              },
              {
                "kind": "text",
                "text": "."
              }
            ],
            "parameters": {
              "builder": [
                {
                  "kind": "text",
                  "text": "The "
                },
                {
                  "kind": "cref",
                  "value": "T:Aspire.Hosting.IDistributedApplicationBuilder"
                },
                {
                  "kind": "text",
                  "text": " to add the resource to."
                }
              ],
              "configFilePaths": [
                {
                  "kind": "text",
                  "text": "The path to the config or schema file(s) for Data API Builder."
                }
              ],
              "httpPort": [
                {
                  "kind": "text",
                  "text": "The HTTP port number for the Data API Builder container."
                }
              ],
              "name": [
                {
                  "kind": "text",
                  "text": "The name of the resource."
                }
              ]
            }
          },
          "sourceFile": "src/CommunityToolkit.Aspire.Hosting.Azure.DataApiBuilder/DataApiBuilderHostingExtension.cs",
          "sourceLines": "48-76"
        }
      ]
    },
    {
      "name": "DataApiBuilderContainerResource",
      "fullName": "Aspire.Hosting.ApplicationModel.DataApiBuilderContainerResource",
      "namespace": "Aspire.Hosting.ApplicationModel",
      "kind": "class",
      "accessibility": "public",
      "baseType": "Aspire.Hosting.ApplicationModel.ContainerResource",
      "interfaces": [
        "Aspire.Hosting.ApplicationModel.IResource",
        "Aspire.Hosting.ApplicationModel.IResourceWithEndpoints",
        "Aspire.Hosting.IResourceWithServiceDiscovery"
      ],
      "docs": {
        "summary": [
          {
            "kind": "text",
            "text": " A resource that represents Data Api Builder. "
          }
        ],
        "parameters": {
          "entrypoint": [
            {
              "kind": "text",
              "text": "An optional container entrypoint."
            }
          ],
          "name": [
            {
              "kind": "text",
              "text": "The name of the resource."
            }
          ]
        }
      },
      "sourceFile": "src/CommunityToolkit.Aspire.Hosting.Azure.DataApiBuilder/DataApiBuilderContainerResource.cs",
      "sourceLines": "10-10",
      "members": [
        {
          "name": ".ctor",
          "kind": "constructor",
          "accessibility": "public",
          "signature": "public DataApiBuilderContainerResource.DataApiBuilderContainerResource(string name, string? entrypoint = null)",
          "returnType": "void",
          "parameters": [
            {
              "name": "name",
              "type": "string"
            },
            {
              "name": "entrypoint",
              "type": "string?",
              "isNullable": true,
              "isOptional": true
            }
          ],
          "docs": {
            "summary": [
              {
                "kind": "text",
                "text": " A resource that represents Data Api Builder. "
              }
            ],
            "parameters": {
              "entrypoint": [
                {
                  "kind": "text",
                  "text": "An optional container entrypoint."
                }
              ],
              "name": [
                {
                  "kind": "text",
                  "text": "The name of the resource."
                }
              ]
            }
          },
          "sourceFile": "src/CommunityToolkit.Aspire.Hosting.Azure.DataApiBuilder/DataApiBuilderContainerResource.cs",
          "sourceLines": "10-10"
        }
      ]
    }
  ]
}