{
  "package": {
    "name": "CommunityToolkit.Aspire.Hosting.SurrealDb",
    "version": "13.1.1",
    "targetFramework": "net10.0",
    "sourceRepository": "https://github.com/CommunityToolkit/Aspire",
    "sourceCommit": "67afcca30f02c18687f9c5219313710af9706630"
  },
  "types": [
    {
      "name": "SurrealDbBuilderExtensions",
      "fullName": "Aspire.Hosting.SurrealDbBuilderExtensions",
      "namespace": "Aspire.Hosting",
      "kind": "class",
      "accessibility": "public",
      "isStatic": true,
      "docs": {
        "summary": [
          {
            "kind": "text",
            "text": " Provides extension methods for adding SurrealDB resources to the application model. "
          }
        ]
      },
      "sourceFile": "src/CommunityToolkit.Aspire.Hosting.SurrealDb/SurrealDbBuilderExtensions.cs",
      "sourceLines": "64-64",
      "members": [
        {
          "name": "AddDatabase",
          "kind": "method",
          "accessibility": "public",
          "signature": "public static IResourceBuilder<SurrealDbDatabaseResource> SurrealDbBuilderExtensions.AddDatabase(this IResourceBuilder<SurrealDbNamespaceResource> builder, string name, string? databaseName = null)",
          "returnType": "Aspire.Hosting.ApplicationModel.IResourceBuilder<Aspire.Hosting.ApplicationModel.SurrealDbDatabaseResource>",
          "isStatic": true,
          "isExtension": true,
          "parameters": [
            {
              "name": "builder",
              "type": "Aspire.Hosting.ApplicationModel.IResourceBuilder<Aspire.Hosting.ApplicationModel.SurrealDbNamespaceResource>",
              "modifier": "this"
            },
            {
              "name": "name",
              "type": "string"
            },
            {
              "name": "databaseName",
              "type": "string?",
              "isNullable": true,
              "isOptional": true
            }
          ],
          "docs": {
            "summary": [
              {
                "kind": "text",
                "text": " Adds a SurrealDB database to the application model. This is a child resource of a "
              },
              {
                "kind": "cref",
                "value": "T:Aspire.Hosting.ApplicationModel.SurrealDbNamespaceResource"
              },
              {
                "kind": "text",
                "text": ". "
              }
            ],
            "remarks": [
              {
                "kind": "text",
                "text": " Add a SurrealDB container to the application model and reference it in a .NET project. "
              },
              {
                "kind": "codeblock",
                "text": "\n             var builder = DistributedApplication.CreateBuilder(args);\n            \n             var db = builder.AddSurrealServer(\"surreal\")\n               .AddNamespace(\"ns\")\n               .AddDatabase(\"db\");\n             var api = builder.AddProject<Projects.Api>(\"api\")\n               .WithReference(db);\n              \n             builder.Build().Run(); \n             ",
                "language": "csharp"
              }
            ],
            "returns": [
              {
                "kind": "text",
                "text": "A reference to the "
              },
              {
                "kind": "cref",
                "value": "T:Aspire.Hosting.ApplicationModel.IResourceBuilder`1"
              },
              {
                "kind": "text",
                "text": "."
              }
            ],
            "parameters": {
              "builder": [
                {
                  "kind": "text",
                  "text": "The SurrealDB resource builders."
                }
              ],
              "databaseName": [
                {
                  "kind": "text",
                  "text": "The name of the database. If not provided, this defaults to the same value as "
                },
                {
                  "kind": "paramref",
                  "value": "name"
                },
                {
                  "kind": "text",
                  "text": "."
                }
              ],
              "name": [
                {
                  "kind": "text",
                  "text": "The name of the resource. This name will be used as the connection string name when referenced in a dependency."
                }
              ]
            }
          },
          "sourceFile": "src/CommunityToolkit.Aspire.Hosting.SurrealDb/SurrealDbBuilderExtensions.cs",
          "sourceLines": "277-311"
        },
        {
          "name": "AddNamespace",
          "kind": "method",
          "accessibility": "public",
          "signature": "public static IResourceBuilder<SurrealDbNamespaceResource> SurrealDbBuilderExtensions.AddNamespace(this IResourceBuilder<SurrealDbServerResource> builder, string name, string? namespaceName = null)",
          "returnType": "Aspire.Hosting.ApplicationModel.IResourceBuilder<Aspire.Hosting.ApplicationModel.SurrealDbNamespaceResource>",
          "isStatic": true,
          "isExtension": true,
          "parameters": [
            {
              "name": "builder",
              "type": "Aspire.Hosting.ApplicationModel.IResourceBuilder<Aspire.Hosting.ApplicationModel.SurrealDbServerResource>",
              "modifier": "this"
            },
            {
              "name": "name",
              "type": "string"
            },
            {
              "name": "namespaceName",
              "type": "string?",
              "isNullable": true,
              "isOptional": true
            }
          ],
          "docs": {
            "summary": [
              {
                "kind": "text",
                "text": " Adds a SurrealDB namespace to the application model. This is a child resource of a "
              },
              {
                "kind": "cref",
                "value": "T:Aspire.Hosting.ApplicationModel.SurrealDbServerResource"
              },
              {
                "kind": "text",
                "text": ". "
              }
            ],
            "remarks": [
              {
                "kind": "text",
                "text": " Add a SurrealDB container to the application model and reference it in a .NET project. "
              },
              {
                "kind": "codeblock",
                "text": "\n             var builder = DistributedApplication.CreateBuilder(args);\n            \n             var db = builder.AddSurrealServer(\"surreal\")\n               .AddNamespace(\"ns\")\n               .AddDatabase(\"db\");\n             var api = builder.AddProject<Projects.Api>(\"api\")\n               .WithReference(db);\n              \n             builder.Build().Run(); \n             ",
                "language": "csharp"
              }
            ],
            "returns": [
              {
                "kind": "text",
                "text": "A reference to the "
              },
              {
                "kind": "cref",
                "value": "T:Aspire.Hosting.ApplicationModel.IResourceBuilder`1"
              },
              {
                "kind": "text",
                "text": "."
              }
            ],
            "parameters": {
              "builder": [
                {
                  "kind": "text",
                  "text": "The SurrealDB resource builders."
                }
              ],
              "name": [
                {
                  "kind": "text",
                  "text": "The name of the resource. This name will be used as the connection string name when referenced in a dependency."
                }
              ],
              "namespaceName": [
                {
                  "kind": "text",
                  "text": "The name of the namespace. If not provided, this defaults to the same value as "
                },
                {
                  "kind": "paramref",
                  "value": "name"
                },
                {
                  "kind": "text",
                  "text": "."
                }
              ]
            }
          },
          "sourceFile": "src/CommunityToolkit.Aspire.Hosting.SurrealDb/SurrealDbBuilderExtensions.cs",
          "sourceLines": "198-225"
        },
        {
          "name": "AddSurrealServer",
          "kind": "method",
          "accessibility": "public",
          "signature": "public static IResourceBuilder<SurrealDbServerResource> SurrealDbBuilderExtensions.AddSurrealServer(this IDistributedApplicationBuilder builder, string name, IResourceBuilder<ParameterResource>? userName = null, IResourceBuilder<ParameterResource>? password = null, int? port = null, string path = \"memory\", bool strictMode = false)",
          "returnType": "Aspire.Hosting.ApplicationModel.IResourceBuilder<Aspire.Hosting.ApplicationModel.SurrealDbServerResource>",
          "isStatic": true,
          "isExtension": true,
          "parameters": [
            {
              "name": "builder",
              "type": "Aspire.Hosting.IDistributedApplicationBuilder",
              "modifier": "this"
            },
            {
              "name": "name",
              "type": "string"
            },
            {
              "name": "userName",
              "type": "Aspire.Hosting.ApplicationModel.IResourceBuilder<Aspire.Hosting.ApplicationModel.ParameterResource>?",
              "isNullable": true,
              "isOptional": true
            },
            {
              "name": "password",
              "type": "Aspire.Hosting.ApplicationModel.IResourceBuilder<Aspire.Hosting.ApplicationModel.ParameterResource>?",
              "isNullable": true,
              "isOptional": true
            },
            {
              "name": "port",
              "type": "int?",
              "isNullable": true,
              "isOptional": true
            },
            {
              "name": "path",
              "type": "string",
              "isOptional": true,
              "defaultValue": "memory"
            },
            {
              "name": "strictMode",
              "type": "bool",
              "isOptional": true,
              "defaultValue": "False"
            }
          ],
          "docs": {
            "summary": [
              {
                "kind": "text",
                "text": " Adds a SurrealDB resource to the application model. A container is used for local development. The default image is "
              },
              {
                "kind": "text",
                "text": " and the tag is "
              },
              {
                "kind": "text",
                "text": ". "
              }
            ],
            "remarks": [
              {
                "kind": "text",
                "text": " Add a SurrealDB container to the application model and reference it in a .NET project. "
              },
              {
                "kind": "codeblock",
                "text": "\n             var builder = DistributedApplication.CreateBuilder(args);\n            \n             var db = builder.AddSurrealServer(\"surreal\")\n               .AddNamespace(\"ns\")\n               .AddDatabase(\"db\");\n             var api = builder.AddProject<Projects.Api>(\"api\")\n               .WithReference(db);\n              \n             builder.Build().Run(); \n             ",
                "language": "csharp"
              }
            ],
            "returns": [
              {
                "kind": "text",
                "text": "A reference to the "
              },
              {
                "kind": "cref",
                "value": "T:Aspire.Hosting.ApplicationModel.IResourceBuilder`1"
              },
              {
                "kind": "text",
                "text": "."
              }
            ],
            "parameters": {
              "builder": [
                {
                  "kind": "text",
                  "text": "The "
                },
                {
                  "kind": "cref",
                  "value": "T:Aspire.Hosting.IDistributedApplicationBuilder"
                },
                {
                  "kind": "text",
                  "text": "."
                }
              ],
              "name": [
                {
                  "kind": "text",
                  "text": "The name of the resource. This name will be used as the connection string name when referenced in a dependency."
                }
              ],
              "password": [
                {
                  "kind": "text",
                  "text": "The parameter used to provide the administrator password for the SurrealDB resource. If "
                },
                {
                  "kind": "langword",
                  "value": "null"
                },
                {
                  "kind": "text",
                  "text": " a random password will be generated."
                }
              ],
              "path": [
                {
                  "kind": "text",
                  "text": "Sets the path for storing data. If no argument is given, the default of "
                },
                {
                  "kind": "code",
                  "text": "memory"
                },
                {
                  "kind": "text",
                  "text": " for non-persistent storage in memory is assumed."
                }
              ],
              "port": [
                {
                  "kind": "text",
                  "text": "The host port for the SurrealDB instance."
                }
              ],
              "strictMode": [
                {
                  "kind": "text",
                  "text": "Whether strict mode is enabled on the server."
                }
              ],
              "userName": [
                {
                  "kind": "text",
                  "text": "The parameter used to provide the administrator username for the SurrealDB resource."
                }
              ]
            }
          },
          "sourceFile": "src/CommunityToolkit.Aspire.Hosting.SurrealDb/SurrealDbBuilderExtensions.cs",
          "sourceLines": "64-111"
        },
        {
          "name": "WithCreationScript",
          "kind": "method",
          "accessibility": "public",
          "signature": "public static IResourceBuilder<SurrealDbNamespaceResource> SurrealDbBuilderExtensions.WithCreationScript(this IResourceBuilder<SurrealDbNamespaceResource> builder, string script)",
          "returnType": "Aspire.Hosting.ApplicationModel.IResourceBuilder<Aspire.Hosting.ApplicationModel.SurrealDbNamespaceResource>",
          "isStatic": true,
          "isExtension": true,
          "parameters": [
            {
              "name": "builder",
              "type": "Aspire.Hosting.ApplicationModel.IResourceBuilder<Aspire.Hosting.ApplicationModel.SurrealDbNamespaceResource>",
              "modifier": "this"
            },
            {
              "name": "script",
              "type": "string"
            }
          ],
          "attributes": [
            {
              "name": "System.Diagnostics.CodeAnalysis.ExperimentalAttribute",
              "constructorArguments": [
                "CTASPIRE002"
              ]
            }
          ],
          "docs": {
            "summary": [
              {
                "kind": "text",
                "text": " Defines the SQL script used to create the namespace. "
              }
            ],
            "remarks": [
              {
                "kind": "text",
                "text": "Default script is "
              },
              {
                "kind": "codeblock",
                "text": "DEFINE NAMESPACE IF NOT EXISTS `QUOTED_NAMESPACE_NAME`;",
                "language": "csharp"
              }
            ],
            "returns": [
              {
                "kind": "text",
                "text": "A reference to the "
              },
              {
                "kind": "cref",
                "value": "T:Aspire.Hosting.ApplicationModel.IResourceBuilder`1"
              },
              {
                "kind": "text",
                "text": "."
              }
            ],
            "parameters": {
              "builder": [
                {
                  "kind": "text",
                  "text": "The builder for the "
                },
                {
                  "kind": "cref",
                  "value": "T:Aspire.Hosting.ApplicationModel.SurrealDbNamespaceResource"
                },
                {
                  "kind": "text",
                  "text": "."
                }
              ],
              "script": [
                {
                  "kind": "text",
                  "text": "The SQL script used to create the namespace."
                }
              ]
            }
          },
          "sourceFile": "src/CommunityToolkit.Aspire.Hosting.SurrealDb/SurrealDbBuilderExtensions.cs"
        },
        {
          "name": "WithCreationScript",
          "kind": "method",
          "accessibility": "public",
          "signature": "public static IResourceBuilder<SurrealDbDatabaseResource> SurrealDbBuilderExtensions.WithCreationScript(this IResourceBuilder<SurrealDbDatabaseResource> builder, string script)",
          "returnType": "Aspire.Hosting.ApplicationModel.IResourceBuilder<Aspire.Hosting.ApplicationModel.SurrealDbDatabaseResource>",
          "isStatic": true,
          "isExtension": true,
          "parameters": [
            {
              "name": "builder",
              "type": "Aspire.Hosting.ApplicationModel.IResourceBuilder<Aspire.Hosting.ApplicationModel.SurrealDbDatabaseResource>",
              "modifier": "this"
            },
            {
              "name": "script",
              "type": "string"
            }
          ],
          "attributes": [
            {
              "name": "System.Diagnostics.CodeAnalysis.ExperimentalAttribute",
              "constructorArguments": [
                "CTASPIRE002"
              ]
            }
          ],
          "docs": {
            "summary": [
              {
                "kind": "text",
                "text": " Defines the SQL script used to create the database. "
              }
            ],
            "remarks": [
              {
                "kind": "text",
                "text": "Default script is "
              },
              {
                "kind": "codeblock",
                "text": "DEFINE DATABASE IF NOT EXISTS `QUOTED_DATABASE_NAME`;",
                "language": "csharp"
              }
            ],
            "returns": [
              {
                "kind": "text",
                "text": "A reference to the "
              },
              {
                "kind": "cref",
                "value": "T:Aspire.Hosting.ApplicationModel.IResourceBuilder`1"
              },
              {
                "kind": "text",
                "text": "."
              }
            ],
            "parameters": {
              "builder": [
                {
                  "kind": "text",
                  "text": "The builder for the "
                },
                {
                  "kind": "cref",
                  "value": "T:Aspire.Hosting.ApplicationModel.SurrealDbDatabaseResource"
                },
                {
                  "kind": "text",
                  "text": "."
                }
              ],
              "script": [
                {
                  "kind": "text",
                  "text": "The SQL script used to create the database."
                }
              ]
            }
          },
          "sourceFile": "src/CommunityToolkit.Aspire.Hosting.SurrealDb/SurrealDbBuilderExtensions.cs"
        },
        {
          "name": "WithDataBindMount",
          "kind": "method",
          "accessibility": "public",
          "signature": "public static IResourceBuilder<SurrealDbServerResource> SurrealDbBuilderExtensions.WithDataBindMount(this IResourceBuilder<SurrealDbServerResource> builder, string source)",
          "returnType": "Aspire.Hosting.ApplicationModel.IResourceBuilder<Aspire.Hosting.ApplicationModel.SurrealDbServerResource>",
          "isStatic": true,
          "isExtension": true,
          "parameters": [
            {
              "name": "builder",
              "type": "Aspire.Hosting.ApplicationModel.IResourceBuilder<Aspire.Hosting.ApplicationModel.SurrealDbServerResource>",
              "modifier": "this"
            },
            {
              "name": "source",
              "type": "string"
            }
          ],
          "docs": {
            "summary": [
              {
                "kind": "text",
                "text": " Adds a bind mount for the data folder to a SurrealDB resource. "
              }
            ],
            "remarks": [
              {
                "kind": "text",
                "text": " Add a SurrealDB container to the application model and reference it in a .NET project. Additionally, in this example a bind mount is added to the container to allow data to be persisted across container restarts. "
              },
              {
                "kind": "codeblock",
                "text": "\n             var builder = DistributedApplication.CreateBuilder(args);\n            \n             var db = builder.AddSurrealServer(\"surreal\")\n               .WithDataBindMount(\"./data/surreal/data\")\n               .AddNamespace(\"ns\")\n               .AddDatabase(\"db\");\n             var api = builder.AddProject<Projects.Api>(\"api\")\n               .WithReference(db);\n              \n             builder.Build().Run(); \n             ",
                "language": "csharp"
              }
            ],
            "returns": [
              {
                "kind": "text",
                "text": "The "
              },
              {
                "kind": "cref",
                "value": "T:Aspire.Hosting.ApplicationModel.IResourceBuilder`1"
              },
              {
                "kind": "text",
                "text": "."
              }
            ],
            "parameters": {
              "builder": [
                {
                  "kind": "text",
                  "text": "The resource builder."
                }
              ],
              "source": [
                {
                  "kind": "text",
                  "text": "The source directory on the host to mount into the container."
                }
              ]
            }
          },
          "sourceFile": "src/CommunityToolkit.Aspire.Hosting.SurrealDb/SurrealDbBuilderExtensions.cs",
          "sourceLines": "393-396"
        },
        {
          "name": "WithDataVolume",
          "kind": "method",
          "accessibility": "public",
          "signature": "public static IResourceBuilder<SurrealDbServerResource> SurrealDbBuilderExtensions.WithDataVolume(this IResourceBuilder<SurrealDbServerResource> builder, string? name = null)",
          "returnType": "Aspire.Hosting.ApplicationModel.IResourceBuilder<Aspire.Hosting.ApplicationModel.SurrealDbServerResource>",
          "isStatic": true,
          "isExtension": true,
          "parameters": [
            {
              "name": "builder",
              "type": "Aspire.Hosting.ApplicationModel.IResourceBuilder<Aspire.Hosting.ApplicationModel.SurrealDbServerResource>",
              "modifier": "this"
            },
            {
              "name": "name",
              "type": "string?",
              "isNullable": true,
              "isOptional": true
            }
          ],
          "docs": {
            "summary": [
              {
                "kind": "text",
                "text": " Adds a named volume for the data folder to a SurrealDB resource. "
              }
            ],
            "remarks": [
              {
                "kind": "text",
                "text": " Add a SurrealDB container to the application model and reference it in a .NET project. Additionally, in this example a data volume is added to the container to allow data to be persisted across container restarts. "
              },
              {
                "kind": "codeblock",
                "text": "\n             var builder = DistributedApplication.CreateBuilder(args);\n            \n             var db = builder.AddSurrealServer(\"surreal\")\n               .WithDataVolume()\n               .AddNamespace(\"ns\")\n               .AddDatabase(\"db\");\n             var api = builder.AddProject<Projects.Api>(\"api\")\n               .WithReference(db);\n              \n             builder.Build().Run(); \n             ",
                "language": "csharp"
              }
            ],
            "returns": [
              {
                "kind": "text",
                "text": "The "
              },
              {
                "kind": "cref",
                "value": "T:Aspire.Hosting.ApplicationModel.IResourceBuilder`1"
              },
              {
                "kind": "text",
                "text": "."
              }
            ],
            "parameters": {
              "builder": [
                {
                  "kind": "text",
                  "text": "The resource builder."
                }
              ],
              "name": [
                {
                  "kind": "text",
                  "text": "The name of the volume. Defaults to an auto-generated name based on the application and resource names."
                }
              ]
            }
          },
          "sourceFile": "src/CommunityToolkit.Aspire.Hosting.SurrealDb/SurrealDbBuilderExtensions.cs",
          "sourceLines": "361-363"
        },
        {
          "name": "WithInitFiles",
          "kind": "method",
          "accessibility": "public",
          "signature": "public static IResourceBuilder<SurrealDbServerResource> SurrealDbBuilderExtensions.WithInitFiles(this IResourceBuilder<SurrealDbServerResource> builder, string source)",
          "returnType": "Aspire.Hosting.ApplicationModel.IResourceBuilder<Aspire.Hosting.ApplicationModel.SurrealDbServerResource>",
          "isStatic": true,
          "isExtension": true,
          "parameters": [
            {
              "name": "builder",
              "type": "Aspire.Hosting.ApplicationModel.IResourceBuilder<Aspire.Hosting.ApplicationModel.SurrealDbServerResource>",
              "modifier": "this"
            },
            {
              "name": "source",
              "type": "string"
            }
          ],
          "attributes": [
            {
              "name": "System.Diagnostics.CodeAnalysis.ExperimentalAttribute",
              "constructorArguments": [
                "CTASPIRE002"
              ]
            }
          ],
          "docs": {
            "summary": [
              {
                "kind": "text",
                "text": " Copies init files into a SurrealDB container resource. "
              }
            ],
            "returns": [
              {
                "kind": "text",
                "text": "The "
              },
              {
                "kind": "cref",
                "value": "T:Aspire.Hosting.ApplicationModel.IResourceBuilder`1"
              },
              {
                "kind": "text",
                "text": "."
              }
            ],
            "parameters": {
              "builder": [
                {
                  "kind": "text",
                  "text": "The resource builder."
                }
              ],
              "source": [
                {
                  "kind": "text",
                  "text": "The source file on the host to copy into the container."
                }
              ]
            },
            "exceptions": [
              {
                "type": "T:Aspire.Hosting.DistributedApplicationException",
                "description": [
                  {
                    "kind": "text",
                    "text": "SurrealDB only support importing a single script file."
                  }
                ]
              }
            ]
          },
          "sourceFile": "src/CommunityToolkit.Aspire.Hosting.SurrealDb/SurrealDbBuilderExtensions.cs",
          "sourceLines": "409-428"
        },
        {
          "name": "WithLogLevel",
          "kind": "method",
          "accessibility": "public",
          "signature": "public static IResourceBuilder<SurrealDbServerResource> SurrealDbBuilderExtensions.WithLogLevel(this IResourceBuilder<SurrealDbServerResource> builder, LogLevel logLevel)",
          "returnType": "Aspire.Hosting.ApplicationModel.IResourceBuilder<Aspire.Hosting.ApplicationModel.SurrealDbServerResource>",
          "isStatic": true,
          "isExtension": true,
          "parameters": [
            {
              "name": "builder",
              "type": "Aspire.Hosting.ApplicationModel.IResourceBuilder<Aspire.Hosting.ApplicationModel.SurrealDbServerResource>",
              "modifier": "this"
            },
            {
              "name": "logLevel",
              "type": "Microsoft.Extensions.Logging.LogLevel"
            }
          ],
          "docs": {
            "summary": [
              {
                "kind": "text",
                "text": " Configures logging level for the SurrealDB container resource. "
              }
            ],
            "returns": [
              {
                "kind": "text",
                "text": "The "
              },
              {
                "kind": "cref",
                "value": "T:Aspire.Hosting.ApplicationModel.IResourceBuilder`1"
              },
              {
                "kind": "text",
                "text": "."
              }
            ],
            "parameters": {
              "builder": [
                {
                  "kind": "text",
                  "text": "The resource builder."
                }
              ],
              "logLevel": [
                {
                  "kind": "text",
                  "text": "The log level to set."
                }
              ]
            }
          },
          "sourceFile": "src/CommunityToolkit.Aspire.Hosting.SurrealDb/SurrealDbBuilderExtensions.cs",
          "sourceLines": "442-452"
        },
        {
          "name": "WithSurrealist",
          "kind": "method",
          "accessibility": "public",
          "signature": "public static IResourceBuilder<T> SurrealDbBuilderExtensions.WithSurrealist<T>(this IResourceBuilder<T> builder, Action<IResourceBuilder<SurrealistContainerResource>>? configureContainer = null, string? containerName = null)",
          "returnType": "Aspire.Hosting.ApplicationModel.IResourceBuilder<T>",
          "isStatic": true,
          "isExtension": true,
          "parameters": [
            {
              "name": "builder",
              "type": "Aspire.Hosting.ApplicationModel.IResourceBuilder<T>",
              "modifier": "this"
            },
            {
              "name": "configureContainer",
              "type": "System.Action<Aspire.Hosting.ApplicationModel.IResourceBuilder<Aspire.Hosting.ApplicationModel.SurrealistContainerResource>>?",
              "isNullable": true,
              "isOptional": true
            },
            {
              "name": "containerName",
              "type": "string?",
              "isNullable": true,
              "isOptional": true
            }
          ],
          "genericParameters": [
            {
              "name": "T",
              "constraints": [
                "Aspire.Hosting.ApplicationModel.SurrealDbServerResource"
              ]
            }
          ],
          "docs": {
            "summary": [
              {
                "kind": "text",
                "text": " Adds a Surrealist UI instance for SurrealDB to the application model. The default image is "
              },
              {
                "kind": "text",
                "text": " and the tag is "
              },
              {
                "kind": "text",
                "text": ". "
              }
            ],
            "returns": [
              {
                "kind": "text",
                "text": "A reference to the "
              },
              {
                "kind": "cref",
                "value": "T:Aspire.Hosting.ApplicationModel.IResourceBuilder`1"
              },
              {
                "kind": "text",
                "text": "."
              }
            ],
            "parameters": {
              "builder": [
                {
                  "kind": "text",
                  "text": "The SurrealDB server resource builder."
                }
              ],
              "configureContainer": [
                {
                  "kind": "text",
                  "text": "Callback to configure Surrealist container resource."
                }
              ],
              "containerName": [
                {
                  "kind": "text",
                  "text": "The name of the container (optional)."
                }
              ]
            }
          },
          "sourceFile": "src/CommunityToolkit.Aspire.Hosting.SurrealDb/SurrealDbBuilderExtensions.cs",
          "sourceLines": "470-517"
        }
      ]
    },
    {
      "name": "SurrealDbDatabaseResource",
      "fullName": "Aspire.Hosting.ApplicationModel.SurrealDbDatabaseResource",
      "namespace": "Aspire.Hosting.ApplicationModel",
      "kind": "class",
      "accessibility": "public",
      "baseType": "Aspire.Hosting.ApplicationModel.Resource",
      "interfaces": [
        "Aspire.Hosting.ApplicationModel.IManifestExpressionProvider",
        "Aspire.Hosting.ApplicationModel.IResource",
        "Aspire.Hosting.ApplicationModel.IResourceWithConnectionString",
        "Aspire.Hosting.ApplicationModel.IResourceWithParent",
        "Aspire.Hosting.ApplicationModel.IResourceWithParent<Aspire.Hosting.ApplicationModel.SurrealDbNamespaceResource>",
        "Aspire.Hosting.ApplicationModel.IValueProvider",
        "Aspire.Hosting.ApplicationModel.IValueWithReferences"
      ],
      "docs": {
        "summary": [
          {
            "kind": "text",
            "text": " A resource that represents a SurrealDB database that is a child of a SurrealDB namespace resource. "
          }
        ]
      },
      "sourceFile": "src/CommunityToolkit.Aspire.Hosting.SurrealDb/SurrealDbDatabaseResource.cs",
      "sourceLines": "14-14",
      "members": [
        {
          "name": ".ctor",
          "kind": "constructor",
          "accessibility": "public",
          "signature": "public SurrealDbDatabaseResource.SurrealDbDatabaseResource(string name, string databaseName, SurrealDbNamespaceResource parent)",
          "returnType": "void",
          "parameters": [
            {
              "name": "name",
              "type": "string"
            },
            {
              "name": "databaseName",
              "type": "string"
            },
            {
              "name": "parent",
              "type": "Aspire.Hosting.ApplicationModel.SurrealDbNamespaceResource"
            }
          ],
          "docs": {
            "summary": [
              {
                "kind": "text",
                "text": " Initializes a new instance of the "
              },
              {
                "kind": "cref",
                "value": "T:Aspire.Hosting.ApplicationModel.SurrealDbDatabaseResource"
              },
              {
                "kind": "text",
                "text": " class. "
              }
            ],
            "parameters": {
              "databaseName": [
                {
                  "kind": "text",
                  "text": "The database name."
                }
              ],
              "name": [
                {
                  "kind": "text",
                  "text": "The name of the resource."
                }
              ],
              "parent": [
                {
                  "kind": "text",
                  "text": "The parent SurrealDB namespace resource."
                }
              ]
            }
          },
          "sourceFile": "src/CommunityToolkit.Aspire.Hosting.SurrealDb/SurrealDbDatabaseResource.cs",
          "sourceLines": "37-44"
        },
        {
          "name": "ConnectionStringExpression",
          "kind": "property",
          "accessibility": "public",
          "signature": "public ReferenceExpression SurrealDbDatabaseResource.ConnectionStringExpression",
          "returnType": "Aspire.Hosting.ApplicationModel.ReferenceExpression",
          "hasGet": true,
          "docs": {
            "summary": [
              {
                "kind": "text",
                "text": " Gets the connection string expression for the SurrealDB database. "
              }
            ]
          },
          "sourceFile": "src/CommunityToolkit.Aspire.Hosting.SurrealDb/SurrealDbDatabaseResource.cs",
          "sourceLines": "20-20"
        },
        {
          "name": "DatabaseName",
          "kind": "property",
          "accessibility": "public",
          "signature": "public string SurrealDbDatabaseResource.DatabaseName",
          "returnType": "string",
          "hasGet": true,
          "docs": {
            "summary": [
              {
                "kind": "text",
                "text": " Gets the database name. "
              }
            ]
          },
          "sourceFile": "src/CommunityToolkit.Aspire.Hosting.SurrealDb/SurrealDbDatabaseResource.cs",
          "sourceLines": "25-25"
        },
        {
          "name": "Parent",
          "kind": "property",
          "accessibility": "public",
          "signature": "public SurrealDbNamespaceResource SurrealDbDatabaseResource.Parent",
          "returnType": "Aspire.Hosting.ApplicationModel.SurrealDbNamespaceResource",
          "hasGet": true,
          "docs": {
            "summary": [
              {
                "kind": "text",
                "text": " Gets the parent SurrealDB namespace resource. "
              }
            ]
          },
          "sourceFile": "src/CommunityToolkit.Aspire.Hosting.SurrealDb/SurrealDbDatabaseResource.cs",
          "sourceLines": "14-14"
        }
      ]
    },
    {
      "name": "SurrealDbNamespaceResource",
      "fullName": "Aspire.Hosting.ApplicationModel.SurrealDbNamespaceResource",
      "namespace": "Aspire.Hosting.ApplicationModel",
      "kind": "class",
      "accessibility": "public",
      "baseType": "Aspire.Hosting.ApplicationModel.Resource",
      "interfaces": [
        "Aspire.Hosting.ApplicationModel.IManifestExpressionProvider",
        "Aspire.Hosting.ApplicationModel.IResource",
        "Aspire.Hosting.ApplicationModel.IResourceWithConnectionString",
        "Aspire.Hosting.ApplicationModel.IResourceWithParent",
        "Aspire.Hosting.ApplicationModel.IResourceWithParent<Aspire.Hosting.ApplicationModel.SurrealDbServerResource>",
        "Aspire.Hosting.ApplicationModel.IValueProvider",
        "Aspire.Hosting.ApplicationModel.IValueWithReferences"
      ],
      "docs": {
        "summary": [
          {
            "kind": "text",
            "text": " A resource that represents a SurrealDB namespace that is a child of a SurrealDB container resource. "
          }
        ]
      },
      "sourceFile": "src/CommunityToolkit.Aspire.Hosting.SurrealDb/SurrealDbNamespaceResource.cs",
      "sourceLines": "14-14",
      "members": [
        {
          "name": ".ctor",
          "kind": "constructor",
          "accessibility": "public",
          "signature": "public SurrealDbNamespaceResource.SurrealDbNamespaceResource(string name, string namespaceName, SurrealDbServerResource parent)",
          "returnType": "void",
          "parameters": [
            {
              "name": "name",
              "type": "string"
            },
            {
              "name": "namespaceName",
              "type": "string"
            },
            {
              "name": "parent",
              "type": "Aspire.Hosting.ApplicationModel.SurrealDbServerResource"
            }
          ],
          "docs": {
            "summary": [
              {
                "kind": "text",
                "text": " Initializes a new instance of the "
              },
              {
                "kind": "cref",
                "value": "T:Aspire.Hosting.ApplicationModel.SurrealDbNamespaceResource"
              },
              {
                "kind": "text",
                "text": " class. "
              }
            ],
            "parameters": {
              "name": [
                {
                  "kind": "text",
                  "text": "The name of the resource."
                }
              ],
              "namespaceName": [
                {
                  "kind": "text",
                  "text": "The namespace name."
                }
              ],
              "parent": [
                {
                  "kind": "text",
                  "text": "The parent SurrealDB server resource."
                }
              ]
            }
          },
          "sourceFile": "src/CommunityToolkit.Aspire.Hosting.SurrealDb/SurrealDbNamespaceResource.cs",
          "sourceLines": "37-46"
        },
        {
          "name": "ConnectionStringExpression",
          "kind": "property",
          "accessibility": "public",
          "signature": "public ReferenceExpression SurrealDbNamespaceResource.ConnectionStringExpression",
          "returnType": "Aspire.Hosting.ApplicationModel.ReferenceExpression",
          "hasGet": true,
          "docs": {
            "summary": [
              {
                "kind": "text",
                "text": " Gets the connection string expression for the SurrealDB database. "
              }
            ]
          },
          "sourceFile": "src/CommunityToolkit.Aspire.Hosting.SurrealDb/SurrealDbNamespaceResource.cs",
          "sourceLines": "20-20"
        },
        {
          "name": "Databases",
          "kind": "property",
          "accessibility": "public",
          "signature": "public IReadOnlyDictionary<string, string> SurrealDbNamespaceResource.Databases",
          "returnType": "System.Collections.Generic.IReadOnlyDictionary<string, string>",
          "hasGet": true,
          "docs": {
            "summary": [
              {
                "kind": "text",
                "text": " A dictionary where the key is the resource name and the value is the database name. "
              }
            ]
          },
          "sourceFile": "src/CommunityToolkit.Aspire.Hosting.SurrealDb/SurrealDbNamespaceResource.cs",
          "sourceLines": "51-51"
        },
        {
          "name": "NamespaceName",
          "kind": "property",
          "accessibility": "public",
          "signature": "public string SurrealDbNamespaceResource.NamespaceName",
          "returnType": "string",
          "hasGet": true,
          "docs": {
            "summary": [
              {
                "kind": "text",
                "text": " Gets the namespace name. "
              }
            ]
          },
          "sourceFile": "src/CommunityToolkit.Aspire.Hosting.SurrealDb/SurrealDbNamespaceResource.cs",
          "sourceLines": "25-25"
        },
        {
          "name": "Parent",
          "kind": "property",
          "accessibility": "public",
          "signature": "public SurrealDbServerResource SurrealDbNamespaceResource.Parent",
          "returnType": "Aspire.Hosting.ApplicationModel.SurrealDbServerResource",
          "hasGet": true,
          "docs": {
            "summary": [
              {
                "kind": "text",
                "text": " Gets the parent SurrealDB container resource. "
              }
            ]
          },
          "sourceFile": "src/CommunityToolkit.Aspire.Hosting.SurrealDb/SurrealDbNamespaceResource.cs",
          "sourceLines": "14-14"
        }
      ]
    },
    {
      "name": "SurrealDbServerResource",
      "fullName": "Aspire.Hosting.ApplicationModel.SurrealDbServerResource",
      "namespace": "Aspire.Hosting.ApplicationModel",
      "kind": "class",
      "accessibility": "public",
      "baseType": "Aspire.Hosting.ApplicationModel.ContainerResource",
      "interfaces": [
        "Aspire.Hosting.ApplicationModel.IManifestExpressionProvider",
        "Aspire.Hosting.ApplicationModel.IResource",
        "Aspire.Hosting.ApplicationModel.IResourceWithConnectionString",
        "Aspire.Hosting.ApplicationModel.IValueProvider",
        "Aspire.Hosting.ApplicationModel.IValueWithReferences"
      ],
      "docs": {
        "summary": [
          {
            "kind": "text",
            "text": " A resource that represents a SurrealDB container. "
          }
        ]
      },
      "sourceFile": "src/CommunityToolkit.Aspire.Hosting.SurrealDb/SurrealDbServerResource.cs",
      "sourceLines": "26-26",
      "members": [
        {
          "name": ".ctor",
          "kind": "constructor",
          "accessibility": "public",
          "signature": "public SurrealDbServerResource.SurrealDbServerResource(string name, ParameterResource? userName, ParameterResource password)",
          "returnType": "void",
          "parameters": [
            {
              "name": "name",
              "type": "string"
            },
            {
              "name": "userName",
              "type": "Aspire.Hosting.ApplicationModel.ParameterResource?",
              "isNullable": true
            },
            {
              "name": "password",
              "type": "Aspire.Hosting.ApplicationModel.ParameterResource"
            }
          ],
          "docs": {
            "summary": [
              {
                "kind": "text",
                "text": " Initializes a new instance of the "
              },
              {
                "kind": "cref",
                "value": "T:Aspire.Hosting.ApplicationModel.SurrealDbServerResource"
              },
              {
                "kind": "text",
                "text": " class. "
              }
            ],
            "parameters": {
              "name": [
                {
                  "kind": "text",
                  "text": "The name of the resource."
                }
              ],
              "password": [
                {
                  "kind": "text",
                  "text": "A parameter that contains the SurrealDB password."
                }
              ],
              "userName": [
                {
                  "kind": "text",
                  "text": "A parameter that contains the SurrealDB username."
                }
              ]
            }
          },
          "sourceFile": "src/CommunityToolkit.Aspire.Hosting.SurrealDb/SurrealDbServerResource.cs",
          "sourceLines": "26-108"
        },
        {
          "name": "GetConnectionStringAsync",
          "kind": "method",
          "accessibility": "public",
          "signature": "public ValueTask<string?> SurrealDbServerResource.GetConnectionStringAsync(CancellationToken cancellationToken = default(CancellationToken))",
          "returnType": "System.Threading.Tasks.ValueTask<string?>",
          "parameters": [
            {
              "name": "cancellationToken",
              "type": "System.Threading.CancellationToken",
              "isOptional": true
            }
          ],
          "docs": {
            "summary": [
              {
                "kind": "text",
                "text": " Gets the connection string for the SurrealDB instance. "
              }
            ],
            "returns": [
              {
                "kind": "text",
                "text": "A connection string for the SurrealDB instance in the form \"Server=scheme://host:port;User=username;Password=password\"."
              }
            ],
            "parameters": {
              "cancellationToken": [
                {
                  "kind": "text",
                  "text": "A "
                },
                {
                  "kind": "cref",
                  "value": "T:System.Threading.CancellationToken"
                },
                {
                  "kind": "text",
                  "text": " to observe while waiting for the task to complete."
                }
              ]
            }
          },
          "sourceFile": "src/CommunityToolkit.Aspire.Hosting.SurrealDb/SurrealDbServerResource.cs",
          "sourceLines": "100-105"
        },
        {
          "name": "ConnectionStringExpression",
          "kind": "property",
          "accessibility": "public",
          "signature": "public ReferenceExpression SurrealDbServerResource.ConnectionStringExpression",
          "returnType": "Aspire.Hosting.ApplicationModel.ReferenceExpression",
          "hasGet": true,
          "docs": {
            "summary": [
              {
                "kind": "text",
                "text": " Gets the connection string expression for the SurrealDB instance. "
              }
            ]
          },
          "sourceFile": "src/CommunityToolkit.Aspire.Hosting.SurrealDb/SurrealDbServerResource.cs",
          "sourceLines": "76-81"
        },
        {
          "name": "Host",
          "kind": "property",
          "accessibility": "public",
          "signature": "public EndpointReferenceExpression SurrealDbServerResource.Host",
          "returnType": "Aspire.Hosting.ApplicationModel.EndpointReferenceExpression",
          "hasGet": true,
          "docs": {
            "summary": [
              {
                "kind": "text",
                "text": " Gets the host endpoint reference for this resource. "
              }
            ]
          },
          "sourceFile": "src/CommunityToolkit.Aspire.Hosting.SurrealDb/SurrealDbServerResource.cs",
          "sourceLines": "43-43"
        },
        {
          "name": "Namespaces",
          "kind": "property",
          "accessibility": "public",
          "signature": "public IReadOnlyDictionary<string, string> SurrealDbServerResource.Namespaces",
          "returnType": "System.Collections.Generic.IReadOnlyDictionary<string, string>",
          "hasGet": true,
          "docs": {
            "summary": [
              {
                "kind": "text",
                "text": " A dictionary where the key is the resource name and the value is the namespace name. "
              }
            ]
          },
          "sourceFile": "src/CommunityToolkit.Aspire.Hosting.SurrealDb/SurrealDbServerResource.cs",
          "sourceLines": "113-113"
        },
        {
          "name": "PasswordParameter",
          "kind": "property",
          "accessibility": "public",
          "signature": "public ParameterResource SurrealDbServerResource.PasswordParameter",
          "returnType": "Aspire.Hosting.ApplicationModel.ParameterResource",
          "hasGet": true,
          "docs": {
            "summary": [
              {
                "kind": "text",
                "text": " Gets the parameter that contains the SurrealDB password. "
              }
            ]
          },
          "sourceFile": "src/CommunityToolkit.Aspire.Hosting.SurrealDb/SurrealDbServerResource.cs",
          "sourceLines": "63-63"
        },
        {
          "name": "Port",
          "kind": "property",
          "accessibility": "public",
          "signature": "public EndpointReferenceExpression SurrealDbServerResource.Port",
          "returnType": "Aspire.Hosting.ApplicationModel.EndpointReferenceExpression",
          "hasGet": true,
          "docs": {
            "summary": [
              {
                "kind": "text",
                "text": " Gets the port endpoint reference for this resource. "
              }
            ]
          },
          "sourceFile": "src/CommunityToolkit.Aspire.Hosting.SurrealDb/SurrealDbServerResource.cs",
          "sourceLines": "48-48"
        },
        {
          "name": "PrimaryEndpoint",
          "kind": "property",
          "accessibility": "public",
          "signature": "public EndpointReference SurrealDbServerResource.PrimaryEndpoint",
          "returnType": "Aspire.Hosting.ApplicationModel.EndpointReference",
          "hasGet": true,
          "docs": {
            "summary": [
              {
                "kind": "text",
                "text": " Gets the primary endpoint for the SurrealDB instance. "
              }
            ]
          },
          "sourceFile": "src/CommunityToolkit.Aspire.Hosting.SurrealDb/SurrealDbServerResource.cs",
          "sourceLines": "38-38"
        },
        {
          "name": "UriExpression",
          "kind": "property",
          "accessibility": "public",
          "signature": "public ReferenceExpression SurrealDbServerResource.UriExpression",
          "returnType": "Aspire.Hosting.ApplicationModel.ReferenceExpression",
          "hasGet": true,
          "docs": {
            "summary": [
              {
                "kind": "text",
                "text": " Gets the connection URI expression for the SurrealDB instance. "
              }
            ],
            "remarks": [
              {
                "kind": "text",
                "text": " Format: "
              },
              {
                "kind": "code",
                "text": "ws://{host}:{port}/rpc"
              },
              {
                "kind": "text",
                "text": ". "
              }
            ]
          },
          "sourceFile": "src/CommunityToolkit.Aspire.Hosting.SurrealDb/SurrealDbServerResource.cs",
          "sourceLines": "91-91"
        },
        {
          "name": "UserNameParameter",
          "kind": "property",
          "accessibility": "public",
          "signature": "public ParameterResource? SurrealDbServerResource.UserNameParameter",
          "returnType": "Aspire.Hosting.ApplicationModel.ParameterResource?",
          "isReturnNullable": true,
          "hasGet": true,
          "docs": {
            "summary": [
              {
                "kind": "text",
                "text": " Gets the parameter that contains the SurrealDB username. "
              }
            ]
          },
          "sourceFile": "src/CommunityToolkit.Aspire.Hosting.SurrealDb/SurrealDbServerResource.cs",
          "sourceLines": "53-53"
        }
      ]
    },
    {
      "name": "SurrealistContainerResource",
      "fullName": "Aspire.Hosting.ApplicationModel.SurrealistContainerResource",
      "namespace": "Aspire.Hosting.ApplicationModel",
      "kind": "class",
      "accessibility": "public",
      "isSealed": true,
      "baseType": "Aspire.Hosting.ApplicationModel.ContainerResource",
      "docs": {
        "summary": [
          {
            "kind": "text",
            "text": " Represents a container resource for Surrealist. "
          }
        ],
        "parameters": {
          "name": [
            {
              "kind": "text",
              "text": "The name of the container resource."
            }
          ]
        }
      },
      "sourceFile": "src/CommunityToolkit.Aspire.Hosting.SurrealDb/SurrealistContainerResource.cs",
      "sourceLines": "10-10",
      "members": [
        {
          "name": ".ctor",
          "kind": "constructor",
          "accessibility": "public",
          "signature": "public SurrealistContainerResource.SurrealistContainerResource(string name)",
          "returnType": "void",
          "parameters": [
            {
              "name": "name",
              "type": "string"
            }
          ],
          "docs": {
            "summary": [
              {
                "kind": "text",
                "text": " Represents a container resource for Surrealist. "
              }
            ],
            "parameters": {
              "name": [
                {
                  "kind": "text",
                  "text": "The name of the container resource."
                }
              ]
            }
          },
          "sourceFile": "src/CommunityToolkit.Aspire.Hosting.SurrealDb/SurrealistContainerResource.cs",
          "sourceLines": "10-10"
        }
      ]
    }
  ]
}