{
  "package": {
    "name": "Aspire.Hosting.Azure.KeyVault",
    "version": "13.1.2",
    "language": "typescript",
    "sourceRepository": "https://github.com/dotnet/aspire"
  },
  "functions": [
    {
      "name": "addAzureKeyVault",
      "capabilityId": "Aspire.Hosting.Azure.KeyVault/addAzureKeyVault",
      "qualifiedName": "addAzureKeyVault",
      "description": "Adds an Azure Key Vault resource",
      "kind": "Method",
      "signature": "addAzureKeyVault(name: string): AzureKeyVaultResource",
      "parameters": [
        {
          "name": "name",
          "type": "string"
        }
      ],
      "returnType": "AzureKeyVaultResource",
      "returnsBuilder": true,
      "targetTypeId": "Aspire.Hosting/Aspire.Hosting.IDistributedApplicationBuilder",
      "expandedTargetTypes": [
        "Aspire.Hosting.IDistributedApplicationBuilder"
      ]
    },
    {
      "name": "addSecret",
      "capabilityId": "Aspire.Hosting.Azure.KeyVault/addSecret",
      "qualifiedName": "addSecret",
      "description": "Adds a secret to the Azure Key Vault from a parameter resource",
      "kind": "Method",
      "signature": "addSecret(name: string, parameterResource: ParameterResource): AzureKeyVaultSecretResource",
      "parameters": [
        {
          "name": "name",
          "type": "string"
        },
        {
          "name": "parameterResource",
          "type": "ParameterResource"
        }
      ],
      "returnType": "AzureKeyVaultSecretResource",
      "returnsBuilder": true,
      "targetTypeId": "Aspire.Hosting.Azure.KeyVault/Aspire.Hosting.Azure.AzureKeyVaultResource",
      "expandedTargetTypes": [
        "Aspire.Hosting.Azure.AzureKeyVaultResource"
      ]
    },
    {
      "name": "addSecretFromExpression",
      "capabilityId": "Aspire.Hosting.Azure.KeyVault/addSecretFromExpression",
      "qualifiedName": "addSecretFromExpression",
      "description": "Adds a secret to the Azure Key Vault from a reference expression",
      "kind": "Method",
      "signature": "addSecretFromExpression(name: string, value: ReferenceExpression): AzureKeyVaultSecretResource",
      "parameters": [
        {
          "name": "name",
          "type": "string"
        },
        {
          "name": "value",
          "type": "ReferenceExpression"
        }
      ],
      "returnType": "AzureKeyVaultSecretResource",
      "returnsBuilder": true,
      "targetTypeId": "Aspire.Hosting.Azure.KeyVault/Aspire.Hosting.Azure.AzureKeyVaultResource",
      "expandedTargetTypes": [
        "Aspire.Hosting.Azure.AzureKeyVaultResource"
      ]
    },
    {
      "name": "addSecretWithName",
      "capabilityId": "Aspire.Hosting.Azure.KeyVault/addSecretWithName",
      "qualifiedName": "addSecretWithName",
      "description": "Adds a named secret to the Azure Key Vault from a parameter resource",
      "kind": "Method",
      "signature": "addSecretWithName(name: string, secretName: string, parameterResource: ParameterResource): AzureKeyVaultSecretResource",
      "parameters": [
        {
          "name": "name",
          "type": "string"
        },
        {
          "name": "secretName",
          "type": "string"
        },
        {
          "name": "parameterResource",
          "type": "ParameterResource"
        }
      ],
      "returnType": "AzureKeyVaultSecretResource",
      "returnsBuilder": true,
      "targetTypeId": "Aspire.Hosting.Azure.KeyVault/Aspire.Hosting.Azure.AzureKeyVaultResource",
      "expandedTargetTypes": [
        "Aspire.Hosting.Azure.AzureKeyVaultResource"
      ]
    },
    {
      "name": "addSecretWithNameFromExpression",
      "capabilityId": "Aspire.Hosting.Azure.KeyVault/addSecretWithNameFromExpression",
      "qualifiedName": "addSecretWithNameFromExpression",
      "description": "Adds a named secret to the Azure Key Vault from a reference expression",
      "kind": "Method",
      "signature": "addSecretWithNameFromExpression(name: string, secretName: string, value: ReferenceExpression): AzureKeyVaultSecretResource",
      "parameters": [
        {
          "name": "name",
          "type": "string"
        },
        {
          "name": "secretName",
          "type": "string"
        },
        {
          "name": "value",
          "type": "ReferenceExpression"
        }
      ],
      "returnType": "AzureKeyVaultSecretResource",
      "returnsBuilder": true,
      "targetTypeId": "Aspire.Hosting.Azure.KeyVault/Aspire.Hosting.Azure.AzureKeyVaultResource",
      "expandedTargetTypes": [
        "Aspire.Hosting.Azure.AzureKeyVaultResource"
      ]
    },
    {
      "name": "getSecret",
      "capabilityId": "Aspire.Hosting.Azure.KeyVault/getSecret",
      "qualifiedName": "getSecret",
      "description": "Gets a secret reference from the Azure Key Vault",
      "kind": "Method",
      "signature": "getSecret(secretName: string): IAzureKeyVaultSecretReference",
      "parameters": [
        {
          "name": "secretName",
          "type": "string"
        }
      ],
      "returnType": "IAzureKeyVaultSecretReference",
      "targetTypeId": "Aspire.Hosting.Azure.KeyVault/Aspire.Hosting.Azure.AzureKeyVaultResource",
      "expandedTargetTypes": [
        "Aspire.Hosting.Azure.AzureKeyVaultResource"
      ]
    },
    {
      "name": "withRoleAssignments",
      "capabilityId": "Aspire.Hosting.Azure.KeyVault/withRoleAssignments",
      "qualifiedName": "withRoleAssignments",
      "description": "Assigns Key Vault roles to a resource",
      "kind": "Method",
      "signature": "withRoleAssignments(target: AzureKeyVaultResource, roles: AzureKeyVaultRole[]): IResource",
      "parameters": [
        {
          "name": "target",
          "type": "AzureKeyVaultResource"
        },
        {
          "name": "roles",
          "type": "AzureKeyVaultRole[]"
        }
      ],
      "returnType": "IResource",
      "returnsBuilder": true,
      "targetTypeId": "Aspire.Hosting/Aspire.Hosting.ApplicationModel.IResource",
      "expandedTargetTypes": [
        "Aspire.Hosting.ApplicationModel.ContainerResource",
        "Aspire.Hosting.ApplicationModel.ExecutableResource",
        "Aspire.Hosting.ApplicationModel.ProjectResource",
        "Aspire.Hosting.ApplicationModel.ParameterResource",
        "Aspire.Hosting.Azure.AzureKeyVaultResource",
        "Aspire.Hosting.Azure.AzureKeyVaultSecretResource"
      ]
    }
  ],
  "handleTypes": [
    {
      "name": "AzureKeyVaultResource",
      "fullName": "Aspire.Hosting.Azure.AzureKeyVaultResource",
      "kind": "handle",
      "implementedInterfaces": [
        "Aspire.Hosting.ApplicationModel.IAzureResource",
        "Aspire.Hosting.ApplicationModel.IManifestExpressionProvider",
        "Aspire.Hosting.ApplicationModel.IResource",
        "Aspire.Hosting.ApplicationModel.IResourceWithConnectionString",
        "Aspire.Hosting.ApplicationModel.IResourceWithEndpoints",
        "Aspire.Hosting.ApplicationModel.IResourceWithParameters",
        "Aspire.Hosting.ApplicationModel.IValueProvider",
        "Aspire.Hosting.ApplicationModel.IValueWithReferences",
        "Aspire.Hosting.Azure.IAzureKeyVaultResource",
        "Aspire.Hosting.Azure.IAzurePrivateEndpointTarget"
      ],
      "capabilities": [
        {
          "name": "addSecret",
          "capabilityId": "Aspire.Hosting.Azure.KeyVault/addSecret",
          "qualifiedName": "addSecret",
          "description": "Adds a secret to the Azure Key Vault from a parameter resource",
          "kind": "Method",
          "signature": "addSecret(name: string, parameterResource: ParameterResource): AzureKeyVaultSecretResource",
          "parameters": [
            {
              "name": "name",
              "type": "string"
            },
            {
              "name": "parameterResource",
              "type": "ParameterResource"
            }
          ],
          "returnType": "AzureKeyVaultSecretResource",
          "returnsBuilder": true,
          "targetTypeId": "Aspire.Hosting.Azure.KeyVault/Aspire.Hosting.Azure.AzureKeyVaultResource",
          "expandedTargetTypes": [
            "Aspire.Hosting.Azure.AzureKeyVaultResource"
          ]
        },
        {
          "name": "addSecretFromExpression",
          "capabilityId": "Aspire.Hosting.Azure.KeyVault/addSecretFromExpression",
          "qualifiedName": "addSecretFromExpression",
          "description": "Adds a secret to the Azure Key Vault from a reference expression",
          "kind": "Method",
          "signature": "addSecretFromExpression(name: string, value: ReferenceExpression): AzureKeyVaultSecretResource",
          "parameters": [
            {
              "name": "name",
              "type": "string"
            },
            {
              "name": "value",
              "type": "ReferenceExpression"
            }
          ],
          "returnType": "AzureKeyVaultSecretResource",
          "returnsBuilder": true,
          "targetTypeId": "Aspire.Hosting.Azure.KeyVault/Aspire.Hosting.Azure.AzureKeyVaultResource",
          "expandedTargetTypes": [
            "Aspire.Hosting.Azure.AzureKeyVaultResource"
          ]
        },
        {
          "name": "addSecretWithName",
          "capabilityId": "Aspire.Hosting.Azure.KeyVault/addSecretWithName",
          "qualifiedName": "addSecretWithName",
          "description": "Adds a named secret to the Azure Key Vault from a parameter resource",
          "kind": "Method",
          "signature": "addSecretWithName(name: string, secretName: string, parameterResource: ParameterResource): AzureKeyVaultSecretResource",
          "parameters": [
            {
              "name": "name",
              "type": "string"
            },
            {
              "name": "secretName",
              "type": "string"
            },
            {
              "name": "parameterResource",
              "type": "ParameterResource"
            }
          ],
          "returnType": "AzureKeyVaultSecretResource",
          "returnsBuilder": true,
          "targetTypeId": "Aspire.Hosting.Azure.KeyVault/Aspire.Hosting.Azure.AzureKeyVaultResource",
          "expandedTargetTypes": [
            "Aspire.Hosting.Azure.AzureKeyVaultResource"
          ]
        },
        {
          "name": "addSecretWithNameFromExpression",
          "capabilityId": "Aspire.Hosting.Azure.KeyVault/addSecretWithNameFromExpression",
          "qualifiedName": "addSecretWithNameFromExpression",
          "description": "Adds a named secret to the Azure Key Vault from a reference expression",
          "kind": "Method",
          "signature": "addSecretWithNameFromExpression(name: string, secretName: string, value: ReferenceExpression): AzureKeyVaultSecretResource",
          "parameters": [
            {
              "name": "name",
              "type": "string"
            },
            {
              "name": "secretName",
              "type": "string"
            },
            {
              "name": "value",
              "type": "ReferenceExpression"
            }
          ],
          "returnType": "AzureKeyVaultSecretResource",
          "returnsBuilder": true,
          "targetTypeId": "Aspire.Hosting.Azure.KeyVault/Aspire.Hosting.Azure.AzureKeyVaultResource",
          "expandedTargetTypes": [
            "Aspire.Hosting.Azure.AzureKeyVaultResource"
          ]
        },
        {
          "name": "getSecret",
          "capabilityId": "Aspire.Hosting.Azure.KeyVault/getSecret",
          "qualifiedName": "getSecret",
          "description": "Gets a secret reference from the Azure Key Vault",
          "kind": "Method",
          "signature": "getSecret(secretName: string): IAzureKeyVaultSecretReference",
          "parameters": [
            {
              "name": "secretName",
              "type": "string"
            }
          ],
          "returnType": "IAzureKeyVaultSecretReference",
          "targetTypeId": "Aspire.Hosting.Azure.KeyVault/Aspire.Hosting.Azure.AzureKeyVaultResource",
          "expandedTargetTypes": [
            "Aspire.Hosting.Azure.AzureKeyVaultResource"
          ]
        }
      ]
    },
    {
      "name": "AzureKeyVaultSecretResource",
      "fullName": "Aspire.Hosting.Azure.AzureKeyVaultSecretResource",
      "kind": "handle",
      "implementedInterfaces": [
        "Aspire.Hosting.ApplicationModel.IManifestExpressionProvider",
        "Aspire.Hosting.ApplicationModel.IResource",
        "Aspire.Hosting.ApplicationModel.IResourceWithParent",
        "Aspire.Hosting.ApplicationModel.IResourceWithParent\u00601[[Aspire.Hosting.Azure.AzureKeyVaultResource, Aspire.Hosting.Azure.KeyVault, Version=42.42.42.42, Culture=neutral, PublicKeyToken=cc7b13ffcd2ddd51]]",
        "Aspire.Hosting.ApplicationModel.IValueProvider",
        "Aspire.Hosting.ApplicationModel.IValueWithReferences",
        "Aspire.Hosting.Azure.IAzureKeyVaultSecretReference"
      ],
      "capabilities": []
    }
  ],
  "dtoTypes": [],
  "enumTypes": [
    {
      "name": "AzureKeyVaultRole",
      "fullName": "Aspire.Hosting.AzureKeyVaultRole",
      "kind": "enum",
      "members": [
        "KeyVaultAdministrator",
        "KeyVaultCertificateUser",
        "KeyVaultCertificatesOfficer",
        "KeyVaultContributor",
        "KeyVaultCryptoOfficer",
        "KeyVaultCryptoServiceEncryptionUser",
        "KeyVaultCryptoServiceReleaseUser",
        "KeyVaultCryptoUser",
        "KeyVaultDataAccessAdministrator",
        "KeyVaultReader",
        "KeyVaultSecretsOfficer",
        "KeyVaultSecretsUser",
        "ManagedHsmContributor"
      ]
    }
  ]
}